sparta_pubsub-0.0.2-py3.11-nspkg.pth
sparta/pubsub/__init__.py
sparta/pubsub/consumer.py
sparta/pubsub/publisher.py
sparta_pubsub-0.0.2.dist-info/LICENSE
sparta_pubsub-0.0.2.dist-info/METADATA
sparta_pubsub-0.0.2.dist-info/WHEEL
sparta_pubsub-0.0.2.dist-info/namespace_packages.txt
sparta_pubsub-0.0.2.dist-info/top_level.txt
sparta_pubsub-0.0.2.dist-info/RECORD
